Workbook

Sheet INPUTS
A2: 1547 Milligan Hwy, Johnson City, TN 37604 | N2: Sources & Uses
A3: SUMMARY | E3: PHOTOS | P3: Loans | Q3: Equity | R3: Total
A4: Asking Price | B4: 2650000 | C4: Offer Price | D4: 2400000 | N4: Price | P4: =F12*D4 -> 1440000 | Q4: =D4-P4-F15 -> 960000 | R4: =SUM(P4:Q4) -> 2400000
A5: Down Payment | C5: 0.4 | D5: =C5*D4 -> 960000 | N5: Renovation | O5: 0.8 | P5: =IF(D9="no",0,D8*O5) -> 0 | Q5: =IF(D9="no",D8,D8-P5) -> 50000 | R5: =SUM(P5:Q5) -> 50000
A6: Number Of Units | D6: 28 | N6: Closing Costs | O6: 0.1 | P6: =D16*O6 -> 14400 | Q6: =D16-P6 -> 129600 | R6: =SUM(P6:Q6) -> 144000
A7: Price Per Unit | D7: =D4/D6 -> 85714.286 | N7: Seller Financing | P7: =$F$15 -> 0
A8: Repair Budget | D8: 50000 | P8: =SUM(P4:P7) -> 1454400 | Q8: =SUM(Q4:Q7) -> 1139600 | R8: =SUM(P8:Q8) -> 2594000
A9: Reno In Loan? | D9: no
A10: Purchase CAP | D10: =D43/D4 -> 0.053204452
A11: Yr 1 Proforma CAP | D11: =G43/D4 -> 0.084685143 | E11: FINANCING
A12: Building Age | D12: 1975 | E12: LTV | F12: =1-C5 -> 0.6 | G12: Senior I/O | H12: 2 | J12: Month | L12: Year
A13: Lot Size | E13: Senior Loan | F13: =P8-F15 -> 1454400 | H13: Principle & Int | J13: ='SENIOR LOAN'!C16 -> 10390.432 | L13: =J13*12 -> 124685.18 | N13: Refinancing
A14: Net RSF | D14: =E35 -> 10528 | E14: Interest Rate | F14: 0.0675 | N14: Refinancing? | R14: Yes
A15: Cost Per Net RSF | D15: =D4/D14 -> 227.96353 | E15: Seller Financing | F15: 0 | H15: Interest Only | J15: ='SENIOR LOAN'!C13 -> 8181 | L15: =J15*12 -> 98172 | N15: Refinance Year (2-6, or enter "0" for no refinance) | R15: 3
A16: Closing Costs | C16: 0.06 | D16: =C16*D4 -> 144000 | E16: Seller Rate | F16: 0 | H16: Seller financing | I16: paid | J16: =F17*H17 -> 0 | N16: Refinance Cap Rate | R16: =R37*(R14="Yes") -> 0.065
A17: Total Equity | D17: =Q8 -> 1139600 | E17: Pmt i/o | F17: =F15*F16 -> 0 | G17: Pay % | H17: 0 | I17: Accrue | J17: =F17-J16 -> 0 | N17: Market Value | R17: =LOOKUP(R$15,PROFORMA!$E$9:$K$9,PROFORMA!$E$40:$K$40)*(R14="Yes") -> 3175546.1
A18: SCHEDULED INCOME | H18: ANNUALIZED EXPENSES | N18: Refinance LTV (%) | R18: 0.6
C19: CURRENT RENTS | F19: PROFORMA RENTS | J19: Current | L19: Proforma | N19: Loan Amount | R19: =R17*R18 -> 1905327.7
A20: UNITS | B20: UNIT TYPE | C20: Monthly Rent/Unit | D20: Monthly Income | E20: SQFT | F20: Monthly Rent/Unit | G20: Monthly Income | H20: Estimated | I20: /unit | K20: /Unit | N20: Years Interest Only (0-9) | R20: 2
A21: 11 | B21: 1BD1BA | C21: 743 | D21: =C21*A21 -> 8173 | E21: 616 | F21: 932 | G21: =F21*A21 -> 10252 | H21: Taxes | I21: =J21/$D$4 -> 0.013691667 | J21: =$B$4*0.0124 -> 32860 | L21: =J21*1.03 -> 33845.8 | N21: Interest Rate | R21: 0.0625
A22: 4 | B22: 2BD1BA | C22: 800 | D22: =C22*A22 -> 3200 | E22: 938 | F22: 1150 | G22: =F22*A22 -> 4600 | H22: Insurance | I22: =J22/$D$6 -> 1500 | J22: 42000 | K22: =L22/$D$6 -> 1500 | L22: 42000 | N22: Loan Amortization (YRS) | R22: 25
A23: 13 | B23: 2BD1.5BA | C23: 1023 | D23: =C23*A23 -> 13299 | F23: 1250 | G23: =F23*A23 -> 16250 | H23: Maint/Repair | I23: =J23/$D$6 -> 1059.3929 | J23: 29663 | K23: =L23/$D$6 -> 700 | L23: 19600 | N23: Closing Costs | R23: 0.02
D24: =C24*A24 -> 0 | G24: =F24*A24 -> 0 | H24: Turnover | I24: =J24/$D$6 -> 0 | J24: 0 | K24: =L24/$D$6 -> 450 | L24: 12600 | N24: Costs of Refinance | R24: =-R23*R19 -> -38106.553
D25: =C25*A25 -> 0 | G25: =F25*A25 -> 0 | H25: Utilities | I25: =J25/$D$6 -> 1550.2143 | J25: 43406 | K25: =L25/$D$6 -> 1596.7143 | L25: 44708 | N25: Senior Loan Pay-Off | R25: =PROFORMA!Q45*($R$14="Yes") -> -1427051
D26: =C26*A26 -> 0 | G26: =F26*A26 -> 0 | H26: Gen/Admin | I26: =J26/$D$6 -> 108.64286 | J26: 3042 | K26: =L26/$D$6 -> 111.89286 | L26: 3133 | N26: Cash Out Amount (Net Cash from REFI) | R26: =R19+R24+R25 -> 440170.12
D27: =C27*A27 -> 0 | G27: =F27*A27 -> 0 | H27: Contract Serv | I27: =J27/$D$6 -> 295.75 | J27: 8281 | K27: =L27/$D$6 -> 304.60714 | L27: 8529 | N27: Amount to investors | R27: =R26 -> 440170.12
D28: =C28*A28 -> 0 | G28: =F28*A28 -> 0 | H28: Marketing | I28: =J28/$D$6 -> 490.17857 | J28: 13725 | K28: =L28/$D$6 -> 0 | L28: 0 | N28: Profits (if any) | R28: =(R27-D17)*(R14="yes") -> -699429.88
D29: =C29*A29 -> 0 | G29: =F29*A29 -> 0 | H29: Landscape / Pest | I29: =J29/$D$6 -> 436.17857 | J29: 12213 | K29: =L29/$D$6 -> 449.28571 | L29: 12580 | N29: Remaining Investor Capital | R29: =(D17-R27)*(R14="yes") -> 699429.88
D30: =C30*A30 -> 0 | G30: =F30*A30 -> 0 | H30: Management | I30: 0.06 | J30: =I30*D41 -> 20417.916 | L30: =I30*G41 -> 24717.456
D31: =C31*A31 -> 0 | G31: =F31*A31 -> 0 | H31: Reserves | I31: 250 | J31: =I31*A35 -> 7000 | L31: =I31*A35 -> 7000
D32: =C32*A32 -> 0 | G32: =F32*A32 -> 0 | H32: Total | J32: =SUM(J21:J31) -> 212607.92 | L32: =SUM(L21:L31) -> 208713.26
D33: =C33*A33 -> 0 | G33: =F33*A33 -> 0 | H33: Expense Ratio | J33: =J32/D41 -> 0.62476871 | L33: =L32/G41 -> 0.50663771 | N33: Sale Inputs
D34: =C34*A34 -> 0 | G34: =F34*A34 -> 0 | H34: Per Unit | J34: =J32/$A$35 -> 7593.1399 | L34: =L32/$A$35 -> 7454.0449
A35: =SUM(A21:A34) -> 28 | D35: =SUM(D21:D34) -> 24672 | E35: =(E21*A21)+(E22*A22)+(E23*A23)+(E24*A24)+(E25*A25)+(E26*A26)+(E27*A27)+(E28*A28)+(E29*A29)+(E30*A30)+(E31*A31)+(E32*A32)+(E33*A33)+(A34*E34) -> 10528 | G35: =SUM(G21:G34) -> 31102 | H35: Per RSF | J35: =J32/$E$35 -> 20.194521 | L35: =L32/$E$35 -> 19.824587 | N35: Sale Year | R35: 6
A36: APOD (ANNUAL PROPERTY OPERATING DATA | N36: Sales Price | R36: =LOOKUP(R$35,PROFORMA!$E$9:$K$9,PROFORMA!$E$40:$K$40) -> 3537682.6
D37: Current | G37: Proforma | N37: Exit/Refi Cap Rate | R37: 0.065
A38: Gross Income: | D38: =D35*12 -> 296064 | G38: =G35*12 -> 373224 | N38: Sales Costs | R38: 0.05
A39: (less) Vacancy/Credit loss: | C39: 0.1 | D39: =-C39*D38 -> -29606.4 | F39: 0.1 | G39: =-F39*G38 -> -37322.4 | N39: Price per unit | R39: =R36/D6 -> 126345.81
A40: Other Income: | D40: 73841 | G40: 76056 | N40: SALE - DETAILS
A41: EGI (Operating Income): | D41: =SUM(D38:D40) -> 340298.6 | G41: =SUM(G38:G40) -> 411957.6 | N41: Sale Price | R41: =R36 -> 3537682.6
A42: (Less) Expenses: | C42: =-D42/D41 -> 0.62476871 | D42: =-J32 -> -212607.92 | F42: =-G42/G41 -> 0.50663771 | G42: =-L32 -> -208713.26 | N42: Less: Principal Remaining On Loan | R42: =SUMIFS(PROFORMA!$F$45:$K$45,PROFORMA!$F$9:$K$9,R35)+SUMIFS(PROFORMA!$F$47:$K$47,PROFORMA!$F$9:$K$9,R35) -> -1866963.3
A43: Net Operating Income NOI: | D43: =SUM(D41:D42) -> 127690.68 | G43: =SUM(G41:G42) -> 203244.34 | N43: Less: Disposition Fee | R43: =-R41*R38 -> -176884.13
A44: (Less) Loan: | B44: DCR | C44: =-D43/D44 -> 1.3006833 | D44: =-IF(H12>=1,L15,L13) -> -98172 | F44: =-G43/G44 -> 2.0702883 | G44: =-IF(H12>=1,L15,L13) -> -98172 | N44: ="Less: Costs of Sale ("&P35*100&"% Sale Price)" -> Less: Costs of Sale (0% Sale Price)
A45: (Less) seller/2nd loan | D45: =-J16 -> 0 | G45: =-J16 -> 0 | N45: Gross Profit | R45: =SUM(R41:R44) -> 1493835.2
A46: Cash Flow: | D46: =SUM(D43:D45) -> 29518.684 | G46: =SUM(G43:G45) -> 105072.34
A47: TOTAL RETURN BEFORE TAX: | D47: =SUM(D46) -> 29518.684 | G47: =SUM(G46) -> 105072.34
A49: METRICS | N49: GP Fees
A50: Cash/Cash yr1: | D50: =D46/D17 -> 0.025902671 | F50: Cash/Cash yr1: | G50: =G46/D17 -> 0.092201074 | N50: AQ Fee | Q50: 0.02 | R50: =Q50*D4 -> 48000
A51: Avg COC | F51: Avg COC | G51: =AVERAGE(PROFORMA!F39:K39) -> 0.071267693 | N51: Asset Management Fee (Monthly) | Q51: 0.01 | R51: =Q51*AVERAGE(PROFORMA!F13:K13) -> 316.3279
A52: Cap Rate | C52: Purchase Cap | D52: =D43/D4 -> 0.053204452 | F52: Sale Cap | G52: =LOOKUP(INPUTS!R35,PROFORMA!E9:K9,PROFORMA!E23:K23)/LOOKUP(INPUTS!R35,PROFORMA!E9:K9,PROFORMA!E40:K40) -> 0.065 | J52: Yr 6 Cap Rate | L52: =PROFORMA!K23/INPUTS!D4 -> 0.095812238 | N52: Refi Fee | Q52: 0.01 | R52: =Q52*R19 -> 19053.277
A53: Equity Multiple | F53: Equity Multiple | G53: =(PROFORMA!E53+PROFORMA!E56)/INPUTS!D17 -> 1.7384478 | K53: Sale Cap | L53: =R37 -> 0.065 | N53: Disposition Fee | Q53: 0 | R53: =Q53*R36 -> 0
A54: IRR | D54: N/A | F54: IRR | G54: =PROFORMA!E52 -> 0.16935243 | K54: Diff | L54: =L52-L53 -> 0.030812238 | N54: Renovation Fee. | Q54: 0.07 | R54: =Q54*D8 -> 3500
A55: 1% Rule | G55: =G35/D4 -> 0.012959167
A56: Return On Cost (% Return On Renovation) | G56: =IF(D8>0,(G35-D35)*12/D8,0) -> 1.5432
A57: NOTES
A58: *ALL THE AREAS IN BLUE ARE FILLABLE CELLS. OTHER CELLS ARE FORMULAS. | N58: Total One Time Fees | R58: =R50+R52+R53+R54 -> 70553.277
A59: * WORKBOOK IS NOT PROTECTED SO YOU CAN EDIT ALL YOU WANT. | N59: Total Monthly Fees | R59: =R51 -> 316.3279

Sheet PROFORMA
B2: =INPUTS!A2 -> 1547 Milligan Hwy, Johnson City, TN 37604
B3: PROFORMA
B5: # of Units | D5: =INPUTS!A35 -> 28
B6: Total Area | D6: =INPUTS!E35 -> 10528
E9: 0 | F9: =E9+1 -> 1 | G9: =F9+1 -> 2 | H9: =G9+1 -> 3 | I9: =H9+1 -> 4 | J9: =I9+1 -> 5 | K9: =J9+1 -> 6 | L9: =K9+1 -> 7 | M9: =L9+1 -> 8 | ... O9: =N9+1 -> 10 | Q9: Total | R9: Avg
E10: 2026 | F10: =E10 -> 2026 | G10: =F10+1 -> 2027 | H10: =G10+1 -> 2028 | I10: =H10+1 -> 2029 | J10: =I10+1 -> 2030 | K10: =J10+1 -> 2031 | L10: =K10+1 -> 2032 | M10: =L10+1 -> 2033 | N10: =M10+1 -> 2034 | O10: =N10+1 -> 2035
B12: Profit & Loss
B13: Gross Monthly Rent | E13: 0 | F13: =INPUTS!D35 -> 24672 | G13: =INPUTS!G35 -> 31102 | H13: =G13*(1+H14)*(H$9<=INPUTS!$R$35) -> 32035.06 | I13: =H13*(1+I14)*(I$9<=INPUTS!$R$35) -> 32996.112 | J13: =I13*(1+J14)*(J$9<=INPUTS!$R$35) -> 33985.995 | K13: =J13*(1+K14)*(K$9<=INPUTS!$R$35) -> 35005.575 | Q13: =SUM(E13:O13) -> 189796.74 | R13: =AVERAGE(E13:O13) -> 27113.82
B14: Rent Bump Increases | E14: n/a | F14: n/a | G14: n/a | H14: 0.03 | I14: 0.03 | J14: 0.03 | K14: 0.03
B15: rent/sqft | E15: =E13/$D$6 -> 0 | F15: =F13/$D$6 -> 2.343465 | G15: =G13/$D$6 -> 2.9542173 | H15: =H13/$D$6 -> 3.0428438 | I15: =I13/$D$6 -> 3.1341292 | J15: =J13/$D$6 -> 3.228153 | K15: =K13/$D$6 -> 3.3249976 | R15: =AVERAGE(E15:O15) -> 2.5754009
B17: Gross Annual Rent | E17: =E13*12 -> 0 | F17: =F13*12 -> 296064 | G17: =G13*12 -> 373224 | H17: =H13*12 -> 384420.72 | I17: =I13*12 -> 395953.34 | J17: =J13*12 -> 407831.94 | K17: =K13*12 -> 420066.9 | Q17: =SUM(E17:O17) -> 2277560.9 | R17: =AVERAGE(E17:O17) -> 325365.84
B18: Less: Economic Loss | E18: =-E19*E17 -> 0 | F18: =-F19*F17 -> -29606.4 | G18: =-G19*G17 -> -37322.4 | H18: =-H19*H17 -> -38442.072 | I18: =-I19*I17 -> -39595.334 | J18: =-J19*J17 -> -40783.194 | K18: =-K19*K17 -> -42006.69 | Q18: =SUM(E18:O18) -> -227756.09 | R18: =AVERAGE(E18:O18) -> -32536.584
B19: Econ Loss Allowance % | E19: =INPUTS!B39 -> 0 | F19: =INPUTS!C39 -> 0.1 | G19: 0.1 | H19: 0.1 | I19: 0.1 | J19: 0.1 | K19: 0.1
B20: Other Income | E20: 0 | F20: =INPUTS!D40 -> 73841 | G20: =INPUTS!G40 -> 76056 | H20: =G20*(1+H22)*(H$9<=INPUTS!$R$35) -> 77577.12 | I20: =H20*(1+I22)*(I$9<=INPUTS!$R$35) -> 79128.662 | J20: =I20*(1+J22)*(J$9<=INPUTS!$R$35) -> 80711.236 | K20: =J20*(1+K22)*(K$9<=INPUTS!$R$35) -> 82325.46 | Q20: =SUM(E20:O20) -> 469639.48 | R20: =AVERAGE(E20:O20) -> 67091.354
B21: Less: Operating expenses | E21: 0 | F21: =INPUTS!G42 -> -208713.26 | G21: =F21*(1+G22) -> -212887.52 | H21: =G21*(1+H22)*(H$9<=INPUTS!$R$35) -> -217145.27 | I21: =H21*(1+I22)*(I$9<=INPUTS!$R$35) -> -221488.18 | J21: =I21*(1+J22)*(J$9<=INPUTS!$R$35) -> -225917.94 | K21: =J21*(1+K22)*(K$9<=INPUTS!$R$35) -> -230436.3 | Q21: =SUM(E21:O21) -> -1316588.5 | R21: =AVERAGE(E21:O21) -> -188084.07
B22: Expense Bump Increases | E22: n/a | F22: n/a | G22: 0.02 | H22: 0.02 | I22: 0.02 | J22: 0.02 | K22: 0.02
B23: NOI | E23: =E17+E18+E20+E21 -> 0 | F23: =F17+F18+F20+F21 -> 131585.34 | G23: =G17+G18+G20+G21 -> 199070.08 | H23: =H17+H18+H20+H21 -> 206410.5 | I23: =I17+I18+I20+I21 -> 213998.49 | J23: =J17+J18+J20+J21 -> 221842.04 | K23: =K17+K18+K20+K21 -> 229949.37 | Q23: =SUM(E23:O23) -> 1202855.8 | R23: =AVERAGE(E23:O23) -> 171836.55
B26: Less: Debt Service P+ I (Senior Loan) | E26: 0 | F26: =IF(INPUTS!$R$14="Yes",F$9<=INPUTS!$R$15,IF(INPUTS!$R$14="No",F$9<INPUTS!$R$35,0))*(-SUMIF('SENIOR LOAN'!$A$22:$A$381,F$9,'SENIOR LOAN'!$E$22:$E$381)-SUMIF('SENIOR LOAN'!$A$22:$A$381,F$9,'SENIOR LOAN'!$F$22:$F$381)*(F$9<=INPUTS!$R$35)) -> -98172 | G26: =IF(INPUTS!$R$14="Yes",G$9<=INPUTS!$R$15,IF(INPUTS!$R$14="No",G$9<INPUTS!$R$35,0))*(-SUMIF('SENIOR LOAN'!$A$22:$A$381,G$9,'SENIOR LOAN'!$E$22:$E$381)-SUMIF('SENIOR LOAN'!$A$22:$A$381,G$9,'SENIOR LOAN'!$F$22:$F$381)*(G$9<=INPUTS!$R$35)) -> -98172 | H26: =IF(INPUTS!$R$14="Yes",H$9<=INPUTS!$R$15,IF(INPUTS!$R$14="No",H$9<INPUTS!$R$35,0))*(-SUMIF('SENIOR LOAN'!$A$22:$A$381,H$9,'SENIOR LOAN'!$E$22:$E$381)-SUMIF('SENIOR LOAN'!$A$22:$A$381,H$9,'SENIOR LOAN'!$F$22:$F$381)*(H$9<=INPUTS!$R$35)) -> -124685.18 | I26: =IF(INPUTS!$R$14="Yes",I$9<=INPUTS!$R$15,IF(INPUTS!$R$14="No",I$9<INPUTS!$R$35,0))*(-SUMIF('SENIOR LOAN'!$A$22:$A$381,I$9,'SENIOR LOAN'!$E$22:$E$381)-SUMIF('SENIOR LOAN'!$A$22:$A$381,I$9,'SENIOR LOAN'!$F$22:$F$381)*(I$9<=INPUTS!$R$35)) -> 0 | J26: =IF(INPUTS!$R$14="Yes",J$9<=INPUTS!$R$15,IF(INPUTS!$R$14="No",J$9<INPUTS!$R$35,0))*(-SUMIF('SENIOR LOAN'!$A$22:$A$381,J$9,'SENIOR LOAN'!$E$22:$E$381)-SUMIF('SENIOR LOAN'!$A$22:$A$381,J$9,'SENIOR LOAN'!$F$22:$F$381)*(J$9<=INPUTS!$R$35)) -> 0 | K26: =IF(INPUTS!$R$14="Yes",K$9<=INPUTS!$R$15,IF(INPUTS!$R$14="No",K$9<INPUTS!$R$35,0))*(-SUMIF('SENIOR LOAN'!$A$22:$A$381,K$9,'SENIOR LOAN'!$E$22:$E$381)-SUMIF('SENIOR LOAN'!$A$22:$A$381,K$9,'SENIOR LOAN'!$F$22:$F$381)*(K$9<=INPUTS!$R$35)) -> 0 | Q26: =SUM(E26:O26) -> -321029.18 | R26: =AVERAGE(E26:O26) -> -45861.312
B27: Less: Debt Service P+ I (REFI Loan) | E27: 0 | F27: =IF(AND(INPUTS!$R$14="Yes",PROFORMA!F$9>INPUTS!$R$15),-SUMIF('REFI LOAN'!$A$22:$A$381,F$9,'REFI LOAN'!$E$22:$E$381)-SUMIF('REFI LOAN'!$A$22:$A$381,F$9,'REFI LOAN'!$F$22:$F$381),0)*(F$9<=INPUTS!$R$35) -> 0 | G27: =IF(AND(INPUTS!$R$14="Yes",PROFORMA!G$9>INPUTS!$R$15),-SUMIF('REFI LOAN'!$A$22:$A$381,G$9,'REFI LOAN'!$E$22:$E$381)-SUMIF('REFI LOAN'!$A$22:$A$381,G$9,'REFI LOAN'!$F$22:$F$381),0)*(G$9<=INPUTS!$R$35) -> 0 | H27: =IF(AND(INPUTS!$R$14="Yes",PROFORMA!H$9>INPUTS!$R$15),-SUMIF('REFI LOAN'!$A$22:$A$381,H$9,'REFI LOAN'!$E$22:$E$381)-SUMIF('REFI LOAN'!$A$22:$A$381,H$9,'REFI LOAN'!$F$22:$F$381),0)*(H$9<=INPUTS!$R$35) -> 0 | I27: =IF(AND(INPUTS!$R$14="Yes",PROFORMA!I$9>INPUTS!$R$15),-SUMIF('REFI LOAN'!$A$22:$A$381,I$9,'REFI LOAN'!$E$22:$E$381)-SUMIF('REFI LOAN'!$A$22:$A$381,I$9,'REFI LOAN'!$F$22:$F$381),0)*(I$9<=INPUTS!$R$35) -> -119082.98 | J27: =IF(AND(INPUTS!$R$14="Yes",PROFORMA!J$9>INPUTS!$R$15),-SUMIF('REFI LOAN'!$A$22:$A$381,J$9,'REFI LOAN'!$E$22:$E$381)-SUMIF('REFI LOAN'!$A$22:$A$381,J$9,'REFI LOAN'!$F$22:$F$381),0)*(J$9<=INPUTS!$R$35) -> -119082.98 | K27: =IF(AND(INPUTS!$R$14="Yes",PROFORMA!K$9>INPUTS!$R$15),-SUMIF('REFI LOAN'!$A$22:$A$381,K$9,'REFI LOAN'!$E$22:$E$381)-SUMIF('REFI LOAN'!$A$22:$A$381,K$9,'REFI LOAN'!$F$22:$F$381),0)*(K$9<=INPUTS!$R$35) -> -156360.71 | Q27: =SUM(E27:O27) -> -394526.67 | R27: =AVERAGE(E27:O27) -> -56360.952
B28: Less: Seller Financing (paid) | E28: 0 | F28: =-INPUTS!$J$16*(INPUTS!$F$15>0)*(IF(INPUTS!$R$14="Yes",F$9<=INPUTS!$R$15,F$9<=INPUTS!$R$35)) -> 0 | G28: =-INPUTS!$J$16*(INPUTS!$F$15>0)*(IF(INPUTS!$R$14="Yes",G$9<=INPUTS!$R$15,G$9<=INPUTS!$R$35)) -> 0 | H28: =-INPUTS!$J$16*(INPUTS!$F$15>0)*(IF(INPUTS!$R$14="Yes",H$9<=INPUTS!$R$15,H$9<=INPUTS!$R$35)) -> 0 | I28: =-INPUTS!$J$16*(INPUTS!$F$15>0)*(IF(INPUTS!$R$14="Yes",I$9<=INPUTS!$R$15,I$9<=INPUTS!$R$35)) -> 0 | J28: =-INPUTS!$J$16*(INPUTS!$F$15>0)*(IF(INPUTS!$R$14="Yes",J$9<=INPUTS!$R$15,J$9<=INPUTS!$R$35)) -> 0 | K28: =-INPUTS!$J$16*(INPUTS!$F$15>0)*(IF(INPUTS!$R$14="Yes",K$9<=INPUTS!$R$15,K$9<=INPUTS!$R$35)) -> 0 | Q28: =SUM(E28:O28) -> 0 | R28: =AVERAGE(E28:O28) -> 0
B29: Accrued Interest (if any) | F29: =INPUTS!$J$17*(INPUTS!$F$15>0)*(IF(INPUTS!$R$14="Yes",F$9<INPUTS!$R$15,F$9<INPUTS!$R$35)) -> 0 | G29: =INPUTS!$J$17*(INPUTS!$F$15>0)*(IF(INPUTS!$R$14="Yes",G$9<INPUTS!$R$15,G$9<INPUTS!$R$35)) -> 0 | H29: =INPUTS!$J$17*(INPUTS!$F$15>0)*(IF(INPUTS!$R$14="Yes",H$9<INPUTS!$R$15,H$9<INPUTS!$R$35)) -> 0 | I29: =INPUTS!$J$17*(INPUTS!$F$15>0)*(IF(INPUTS!$R$14="Yes",I$9<INPUTS!$R$15,I$9<INPUTS!$R$35)) -> 0 | J29: =INPUTS!$J$17*(INPUTS!$F$15>0)*(IF(INPUTS!$R$14="Yes",J$9<INPUTS!$R$15,J$9<INPUTS!$R$35)) -> 0 | K29: =INPUTS!$J$17*(INPUTS!$F$15>0)*(IF(INPUTS!$R$14="Yes",K$9<INPUTS!$R$15,K$9<INPUTS!$R$35)) -> 0 | Q29: =SUM(E29:O29) -> 0
B30: Free Cashflows | E30: =E23+E26+E27+E28 -> 0 | F30: =F23+F26+F27+F28 -> 33413.344 | G30: =G23+G26+G27+G28 -> 100898.08 | H30: =H23+H26+H27+H28 -> 81725.312 | I30: =I23+I26+I27+I28 -> 94915.514 | J30: =J23+J26+J27+J28 -> 102759.06 | K30: =K23+K26+K27+K28 -> 73588.662 | Q30: =SUM(E30:O30) -> 487299.97 | R30: =AVERAGE(E30:O30) -> 69614.282
B32: Net Cash from Refinance
B33: REFI Proceeds | E33: =(E$9=INPUTS!$R$15)*INPUTS!$R$19 -> 0 | F33: =(F$9=INPUTS!$R$15)*INPUTS!$R$19 -> 0 | G33: =(G$9=INPUTS!$R$15)*INPUTS!$R$19 -> 0 | H33: =(H$9=INPUTS!$R$15)*INPUTS!$R$19 -> 1905327.7 | I33: =(I$9=INPUTS!$R$15)*INPUTS!$R$19 -> 0 | J33: =(J$9=INPUTS!$R$15)*INPUTS!$R$19 -> 0 | K33: =(K$9=INPUTS!$R$15)*INPUTS!$R$19 -> 0 | Q33: =SUM(E33:O33) -> 1905327.7
B34: Less: Senior Loan Pay-off | E34: =E45*(E33>0) -> 0 | F34: =F45*(F33>0) -> 0 | G34: =G45*(G33>0) -> 0 | H34: =H45*(H33>0) -> -1427051 | I34: =I45*(I33>0) -> 0 | J34: =J45*(J33>0) -> 0 | K34: =K45*(K33>0) -> 0 | Q34: =SUM(E34:O34) -> -1427051
B35: Less: Seller Financing+Int | E35: =E46*(E33>0) -> 0 | F35: =F46*(F33>0) -> 0 | G35: =G46*(G33>0) -> 0 | H35: =H46*(H33>0) -> 0 | I35: =I46*(I33>0) -> 0 | J35: =J46*(J33>0) -> 0 | K35: =K46*(K33>0) -> 0
B36: Less: Costs of REFI (if any) | E36: =E48 -> 0 | F36: =F48 -> 0 | G36: =G48 -> 0 | H36: =H48 -> -38106.553 | I36: =I48 -> 0 | J36: =J48 -> 0 | K36: =K48 -> 0 | Q36: =SUM(E36:O36) -> -38106.553
B37: Net Cash | E37: =SUM(E33:E36) -> 0 | F37: =SUM(F33:F36) -> 0 | G37: =SUM(G33:G36) -> 0 | H37: =SUM(H33:H36) -> 440170.12 | I37: =SUM(I33:I36) -> 0 | J37: =SUM(J33:J36) -> 0 | K37: =SUM(K33:K36) -> 0 | Q37: =SUM(E37:O37) -> 440170.12
B39: Cash/ Cash Return | F39: =F30/INPUTS!$D$17 -> 0.029320239 | G39: =G30/INPUTS!$D$17 -> 0.088538153 | H39: =H30/INPUTS!$D$17 -> 0.071714033 | I39: =I30/INPUTS!$D$17 -> 0.083288447 | J39: =J30/INPUTS!$D$17 -> 0.090171169 | K39: =K30/INPUTS!$D$17 -> 0.064574115 | Q39: =Q30/-E49 -> 0.42760616 | R39: =AVERAGE(E39:O39) -> 0.071267693
B40: Estimated Market Value | E40: =E23/E41 -> 0 | F40: =F23/F41 -> 2024389.9 | G40: =G23/G41 -> 3062616.6 | H40: =H23/H41 -> 3175546.1 | I40: =I23/I41 -> 3292284.5 | J40: =J23/J41 -> 3412954.5 | K40: =K23/K41 -> 3537682.6 | Q40: =MAX(F43:O43) -> 3537682.6 | R40: =K40 -> 3537682.6
B41: Exit Cap Rate | E41: =INPUTS!$R$37 -> 0.065 | F41: =INPUTS!$R$37 -> 0.065 | G41: =INPUTS!$R$37 -> 0.065 | H41: =INPUTS!$R$37 -> 0.065 | I41: =INPUTS!$R$37 -> 0.065 | J41: =INPUTS!$R$37 -> 0.065 | K41: =INPUTS!$R$37 -> 0.065
B43: Gross Sale Proceeds | F43: =(F$9=INPUTS!$R$35)*F40 -> 0 | G43: =(G$9=INPUTS!$R$35)*G40 -> 0 | H43: =(H$9=INPUTS!$R$35)*H40 -> 0 | I43: =(I$9=INPUTS!$R$35)*I40 -> 0 | J43: =(J$9=INPUTS!$R$35)*J40 -> 0 | K43: =(K$9=INPUTS!$R$35)*K40 -> 3537682.6 | Q43: =MAX(E43:O43) -> 3537682.6
B44: Less: Selling costs | D44: =INPUTS!R38 -> 0.05 | F44: =-F43*$D44 -> 0 | G44: =-G43*$D44 -> 0 | H44: =-H43*$D44 -> 0 | I44: =-I43*$D44 -> 0 | J44: =-J43*$D44 -> 0 | K44: =-K43*$D44 -> -176884.13 | Q44: =MIN(E44:O44) -> -176884.13
B45: Less: Senior Loan Pay-off | F45: =-IF(AND(INPUTS!$R$14="Yes",F$9=INPUTS!$R$15),LOOKUP(INPUTS!$R$15*12,'SENIOR LOAN'!$B$22:$B$381,'SENIOR LOAN'!$G$22:$G$381),IF(AND(INPUTS!$R$14="No",F$9=INPUTS!$R$35),LOOKUP(INPUTS!$R$35*12,'SENIOR LOAN'!$B$22:$B$381,'SENIOR LOAN'!$G$22:$G$381))) -> 0 | G45: =-IF(AND(INPUTS!$R$14="Yes",G$9=INPUTS!$R$15),LOOKUP(INPUTS!$R$15*12,'SENIOR LOAN'!$B$22:$B$381,'SENIOR LOAN'!$G$22:$G$381),IF(AND(INPUTS!$R$14="No",G$9=INPUTS!$R$35),LOOKUP(INPUTS!$R$35*12,'SENIOR LOAN'!$B$22:$B$381,'SENIOR LOAN'!$G$22:$G$381))) -> 0 | H45: =-IF(AND(INPUTS!$R$14="Yes",H$9=INPUTS!$R$15),LOOKUP(INPUTS!$R$15*12,'SENIOR LOAN'!$B$22:$B$381,'SENIOR LOAN'!$G$22:$G$381),IF(AND(INPUTS!$R$14="No",H$9=INPUTS!$R$35),LOOKUP(INPUTS!$R$35*12,'SENIOR LOAN'!$B$22:$B$381,'SENIOR LOAN'!$G$22:$G$381))) -> -1427051 | I45: =-IF(AND(INPUTS!$R$14="Yes",I$9=INPUTS!$R$15),LOOKUP(INPUTS!$R$15*12,'SENIOR LOAN'!$B$22:$B$381,'SENIOR LOAN'!$G$22:$G$381),IF(AND(INPUTS!$R$14="No",I$9=INPUTS!$R$35),LOOKUP(INPUTS!$R$35*12,'SENIOR LOAN'!$B$22:$B$381,'SENIOR LOAN'!$G$22:$G$381))) -> 0 | J45: =-IF(AND(INPUTS!$R$14="Yes",J$9=INPUTS!$R$15),LOOKUP(INPUTS!$R$15*12,'SENIOR LOAN'!$B$22:$B$381,'SENIOR LOAN'!$G$22:$G$381),IF(AND(INPUTS!$R$14="No",J$9=INPUTS!$R$35),LOOKUP(INPUTS!$R$35*12,'SENIOR LOAN'!$B$22:$B$381,'SENIOR LOAN'!$G$22:$G$381))) -> 0 | K45: =-IF(AND(INPUTS!$R$14="Yes",K$9=INPUTS!$R$15),LOOKUP(INPUTS!$R$15*12,'SENIOR LOAN'!$B$22:$B$381,'SENIOR LOAN'!$G$22:$G$381),IF(AND(INPUTS!$R$14="No",K$9=INPUTS!$R$35),LOOKUP(INPUTS!$R$35*12,'SENIOR LOAN'!$B$22:$B$381,'SENIOR LOAN'!$G$22:$G$381))) -> 0 | Q45: =MIN(E45:O45) -> -1427051
B46: Less: Seller Financing+Int | F46: {=-IF(INPUTS!$F$15>0,IF(OR(AND(INPUTS!$R$14="Yes",F$9=INPUTS!$R$15),AND(F$9=INPUTS!$R$35,SUMPRODUCT((INPUTS!$R$14="Yes")*(E$9:$F$9=INPUTS!$R$15))=0)),INPUTS!$F$15+SUM($F29:F29),0),0)} -> 0 | G46: {=-IF(INPUTS!$F$15>0,IF(OR(AND(INPUTS!$R$14="Yes",G$9=INPUTS!$R$15),AND(G$9=INPUTS!$R$35,SUMPRODUCT((INPUTS!$R$14="Yes")*(F$9:$F$9=INPUTS!$R$15))=0)),INPUTS!$F$15+SUM($F29:G29),0),0)} -> 0 | H46: {=-IF(INPUTS!$F$15>0,IF(OR(AND(INPUTS!$R$14="Yes",H$9=INPUTS!$R$15),AND(H$9=INPUTS!$R$35,SUMPRODUCT((INPUTS!$R$14="Yes")*($F$9:G$9=INPUTS!$R$15))=0)),INPUTS!$F$15+SUM($F29:H29),0),0)} -> 0 | I46: {=-IF(INPUTS!$F$15>0,IF(OR(AND(INPUTS!$R$14="Yes",I$9=INPUTS!$R$15),AND(I$9=INPUTS!$R$35,SUMPRODUCT((INPUTS!$R$14="Yes")*($F$9:H$9=INPUTS!$R$15))=0)),INPUTS!$F$15+SUM($F29:I29),0),0)} -> 0 | J46: {=-IF(INPUTS!$F$15>0,IF(OR(AND(INPUTS!$R$14="Yes",J$9=INPUTS!$R$15),AND(J$9=INPUTS!$R$35,SUMPRODUCT((INPUTS!$R$14="Yes")*($F$9:I$9=INPUTS!$R$15))=0)),INPUTS!$F$15+SUM($F29:J29),0),0)} -> 0 | K46: {=-IF(INPUTS!$F$15>0,IF(OR(AND(INPUTS!$R$14="Yes",K$9=INPUTS!$R$15),AND(K$9=INPUTS!$R$35,SUMPRODUCT((INPUTS!$R$14="Yes")*($F$9:J$9=INPUTS!$R$15))=0)),INPUTS!$F$15+SUM($F29:K29),0),0)} -> 0
B47: Less: REFI Loan Pay-off (if any) | F47: =-IFERROR(IF(AND(INPUTS!$R$14="Yes",F$9=INPUTS!$R$35),LOOKUP(INPUTS!$R$35*12,'REFI LOAN'!$B$22:$B$381,'REFI LOAN'!$G$22:$G$381),0),0) -> 0 | G47: =-IFERROR(IF(AND(INPUTS!$R$14="Yes",G$9=INPUTS!$R$35),LOOKUP(INPUTS!$R$35*12,'REFI LOAN'!$B$22:$B$381,'REFI LOAN'!$G$22:$G$381),0),0) -> 0 | H47: =-IFERROR(IF(AND(INPUTS!$R$14="Yes",H$9=INPUTS!$R$35),LOOKUP(INPUTS!$R$35*12,'REFI LOAN'!$B$22:$B$381,'REFI LOAN'!$G$22:$G$381),0),0) -> 0 | I47: =-IFERROR(IF(AND(INPUTS!$R$14="Yes",I$9=INPUTS!$R$35),LOOKUP(INPUTS!$R$35*12,'REFI LOAN'!$B$22:$B$381,'REFI LOAN'!$G$22:$G$381),0),0) -> 0 | J47: =-IFERROR(IF(AND(INPUTS!$R$14="Yes",J$9=INPUTS!$R$35),LOOKUP(INPUTS!$R$35*12,'REFI LOAN'!$B$22:$B$381,'REFI LOAN'!$G$22:$G$381),0),0) -> 0 | K47: =-IFERROR(IF(AND(INPUTS!$R$14="Yes",K$9=INPUTS!$R$35),LOOKUP(INPUTS!$R$35*12,'REFI LOAN'!$B$22:$B$381,'REFI LOAN'!$G$22:$G$381),0),0) -> -1866963.3 | Q47: =MIN(E47:O47) -> -1866963.3
B48: Less: Costs of REFI (if any) | F48: =(INPUTS!$R$14="Yes")*(F$9=INPUTS!$R$15)*INPUTS!$R$24 -> 0 | G48: =(INPUTS!$R$14="Yes")*(G$9=INPUTS!$R$15)*INPUTS!$R$24 -> 0 | H48: =(INPUTS!$R$14="Yes")*(H$9=INPUTS!$R$15)*INPUTS!$R$24 -> -38106.553 | I48: =(INPUTS!$R$14="Yes")*(I$9=INPUTS!$R$15)*INPUTS!$R$24 -> 0 | J48: =(INPUTS!$R$14="Yes")*(J$9=INPUTS!$R$15)*INPUTS!$R$24 -> 0 | K48: =(INPUTS!$R$14="Yes")*(K$9=INPUTS!$R$15)*INPUTS!$R$24 -> 0 | Q48: =MIN(E48:O48) -> -38106.553
B49: Levered Cashflows | E49: =-INPUTS!D17 -> -1139600 | F49: =F30+F33+F43+F44+F45+F46+F47+F48 -> 33413.344 | G49: =G30+G33+G43+G44+G45+G46+G47+G48 -> 100898.08 | H49: =H30+H33+H43+H44+H45+H46+H47+H48 -> 521895.43 | I49: =I30+I33+I43+I44+I45+I46+I47+I48 -> 94915.514 | J49: =J30+J33+J43+J44+J45+J46+J47+J48 -> 102759.06 | K49: =K30+K33+K43+K44+K45+K46+K47+K48 -> 1567423.8 | Q49: =SUM(E49:K49) -> 1281705.3
B51: METRICS
B52: Leveraged IRR | E52: =IRR(E49:K49) -> 0.16935243
B53: Net Proceeds From Sale | E53: =Q43+Q44+INPUTS!R42 -> 1493835.2
B54: Gross Proceeds From Sale | E54: =Q43 -> 3537682.6
B55: Selling Costs | E55: =Q44 -> -176884.13
B56: Total Free Cashflow | E56: =Q30 -> 487299.97
B57: =B32 -> Net Cash from Refinance | E57: =Q37 -> 440170.12
B58: Initial Investment | E58: =E49 -> -1139600
B59: Loan Pay-Offs | E59: =INPUTS!R42 -> -1866963.3
B60: Net Total Profits | E60: =SUM(E54:E59) -> 1281705.3
B61: ROI | E61: =E60/-E58 -> 1.1246975
E62: Equity | F62: Profit Split
C63: EQUITY PARTNER | D63: 0.9 | E63: =-E58*D63 -> 1025640 | F63: 0.65
C64: SPONSOR | D64: 0.1 | E64: =-E58*D64 -> 113960 | F64: 0.35
C65: Total | D65: =SUM(D63:D64) -> 1 | E65: =SUM(E63:E64) -> 1139600 | F65: =SUM(F63:F64) -> 1
E67: PREFERRED RETURN | F67: PROFIT | G67: TOTAL | H67: ROI | I67: IRR - Annual Return
C68: Equity Partner | D68: 0.1 | E68: =D68*E63 -> 102564 | F68: =(E60-E68)*F63 -> 766441.83 | G68: =SUM(E68:F68) -> 869005.83 | H68: =G68/E63 -> 0.84728153 | I68: =H68/6 -> 0.14121359
C69: Sponsor | F69: =E60-G68 -> 412699.45 | G69: =SUM(E69:F69) -> 412699.45 | H69: =G69/E64 -> 3.6214413 | I69: =H69/6 -> 0.60357354
B70: Check | E70: =E60-SUM(E49:K49) -> 0

Sheet WATERFALL
D2: =INPUTS!A2 -> 1547 Milligan Hwy, Johnson City, TN 37604
D3: Equity Waterfall
B4: Equity Structure | C4: % | F4: 0 | G4: =F4+1 -> 1 | H4: =G4+1 -> 2 | I4: =H4+1 -> 3 | J4: =I4+1 -> 4 | K4: =J4+1 -> 5 | L4: =K4+1 -> 6 | M4: =L4+1 -> 7 | N4: =M4+1 -> 8 | ... P4: =O4+1 -> 10
B5: GP Equity Contribution | C5: 0.1 | D5: =C5*INPUTS!$D$17 -> 113960 | F5: =PROFORMA!E10 -> 2026 | G5: =PROFORMA!F10 -> 2026 | H5: =G5+1 -> 2027 | I5: =H5+1 -> 2028 | J5: =I5+1 -> 2029 | K5: =J5+1 -> 2030 | L5: =K5+1 -> 2031 | M5: =L5+1 -> 2032 | N5: =M5+1 -> 2033 | O5: =N5+1 -> 2034 | P5: =O5+1 -> 2035
B6: LP Equity Contribution | C6: 0.9 | D6: =C6*INPUTS!$D$17 -> 1025640
B7: Return Hurdles | C7: Preferred Return | D7: GP Return | E7: LP Return
B8: Hurdle 1: (Preferred Return) | C8: 0.06 | D8: 0 | E8: 1
B9: Hurdle 2 split: | C9: 0 | D9: 0.5 | E9: 0.5
B10: Hurdle 3 split: | C10: Profits Splits | D10: 0.2 | E10: 0.8
B11: LP IRR Take Out % | C11: 0.15
B12: Project Level Levered Cash Flow | D12: IRR | E12: =IRR(F12:P12) -> 0.16935243 | F12: =PROFORMA!E49 -> -1139600 | G12: =PROFORMA!F49 -> 33413.344 | H12: =PROFORMA!G49 -> 100898.08 | I12: =PROFORMA!H49 -> 521895.43 | J12: =PROFORMA!I49 -> 94915.514 | K12: =PROFORMA!J49 -> 102759.06 | L12: =PROFORMA!K49 -> 1567423.8 | M12: =PROFORMA!L49 -> 0 | ... P12: =PROFORMA!O49 -> 0
B14: Hurdle 1 Pref Return
B15: Beginning Balance (LP) | F15: =E20 -> 0 | G15: =F20 -> 1025640 | H15: =G20 -> 1025640 | I15: =H20 -> 1016652.3 | J15: =I20 -> 647935.27 | K15: =J20 -> 603103.75 | L15: =K20 -> 549845.48 | M15: =L20 -> 0 | ... P15: =O20 -> 0
B16: LP Preferred Balance | C16: =C8 -> 0.06 | F16: =F15*$C16 -> 0 | G16: =G15*$C16 -> 61538.4 | H16: =(H$15*$C$16)+G19 -> 89663.456 | I16: =(I$15*$C$16)+H19 -> 60999.138 | J16: =(J15*$C$16)+I19 -> 38876.116 | K16: =(K15*$C$16)+J19 -> 36186.225 | L16: =(L15*$C$16)+K19 -> 32990.729 | M16: =M15*$C16 -> 0 | N16: =N15*$C16 -> 0 | O16: =O15*$C16 -> 0 | P16: =P15*$C16 -> 0
B17: LP Contributions | C17: =C6 -> 0.9 | F17: =-MIN(F12,0)*$C$17 -> 1025640 | G17: =-MIN(G12,0)*$C$17 -> 0 | H17: =-MIN(H12,0)*$C$17 -> 0 | I17: =-MIN(I12,0)*$C$17 -> 0 | J17: =-MIN(J12,0)*$C$17 -> 0 | K17: =-MIN(K12,0)*$C$17 -> 0 | L17: =-MIN(L12,0)*$C$17 -> 0 | M17: =-MIN(M12,0)*$C$17 -> 0 | ... P17: =-MIN(P12,0)*$C$17 -> 0
B18: LP Pref Distributions | C18: =E8 -> 1 | F18: =MIN(F15+F16,MAX(F12,0)*$C18) -> 0 | G18: =MIN(G15+G16,MAX(G12,0)*$C18) -> 33413.344 | H18: =MIN(H16,MAX(H12,0)*$C18) -> 89663.456 | I18: =MIN(I16,MAX(I12,0)*$C18) -> 60999.138 | J18: =MIN(J16,MAX(J12,0)*$C18) -> 38876.116 | K18: =MIN(K16,MAX(K12,0)*$C18) -> 36186.225 | L18: =MIN(L16,MAX(L12,0)*$C18) -> 32990.729 | M18: =MIN(M15+M16,MAX(M12,0)*$C18) -> 0 | N18: =MIN(N15+N16,MAX(N12,0)*$C18) -> 0 | O18: =MIN(O15+O16,MAX(O12,0)*$C18) -> 0 | P18: =MIN(P15+P16,MAX(P12,0)*$C18) -> 0
B19: Unpaid Pref | F19: =F16-F18 -> 0 | G19: =G16-G18 -> 28125.056 | H19: =H16-H18 -> 0 | I19: =I16-I18 -> 0 | J19: =J16-J18 -> 0 | K19: =K16-K18 -> 0 | L19: =L16-L18 -> 0
B20: Ending Balance (LP) | F20: =MAX(0,F15+F17-F53) -> 1025640 | G20: =MAX(0,G15+G17-G53) -> 1025640 | H20: =MAX(0,H15+H17-H53) -> 1016652.3 | I20: =MAX(0,I15+I17-I53) -> 647935.27 | J20: =MAX(0,J15+J17-J53) -> 603103.75 | K20: =MAX(0,K15+K17-K53) -> 549845.48 | L20: =MAX(0,L15+L17-L53) -> 0 | M20: =MAX(0,M15+M16+M17-M18) -> 0 | N20: =MAX(0,N15+N16+N17-N18) -> 0 | O20: =MAX(0,O15+O16+O17-O18) -> 0 | P20: =MAX(0,P15+P16+P17-P18) -> 0
B21: LP Pref % Cash Distribution | C21: =C16 -> 0.06 | F21: =F18/SUM($E17:F17) -> 0 | G21: =G18/SUM($E17:G17) -> 0.032578043 | H21: =H18/SUM($E17:H17) -> 0.087421957 | I21: =I18/SUM($E17:I17) -> 0.059474219 | J21: =J18/SUM($E17:J17) -> 0.037904251 | K21: =K18/SUM($E17:K17) -> 0.035281605 | L21: =L18/SUM($E17:L17) -> 0.032165993 | M21: =M18/SUM($E17:M17) -> 0 | ... P21: =P18/SUM($E17:P17) -> 0
B22: LP Net Cash Flows | F22: =-F17+F18 -> -1025640 | G22: =-G17+G18 -> 33413.344 | H22: =-H17+H18 -> 89663.456 | I22: =-I17+I18 -> 60999.138 | J22: =-J17+J18 -> 38876.116 | K22: =-K17+K18 -> 36186.225 | L22: =-L17+L18 -> 32990.729 | M22: =-M17+M18 -> 0 | ... P22: =-P17+P18 -> 0
B23: LP IRR Check | C23: =ROUND(IRR(F22:L22),3)=C21 -> FALSE
B25: Contributions from GP | C25: =C5 -> 0.1 | F25: =-MIN(F12,0)*$C$25 -> 113960 | G25: =-MIN(G12,0)*$C$25 -> 0 | H25: =-MIN(H12,0)*$C$25 -> 0 | I25: =-MIN(I12,0)*$C$25 -> 0 | J25: =-MIN(J12,0)*$C$25 -> 0 | K25: =-MIN(K12,0)*$C$25 -> 0 | L25: =-MIN(L12,0)*$C$25 -> 0 | M25: =-MIN(M12,0)*$C$25 -> 0 | ... P25: =-MIN(P12,0)*$C$25 -> 0
B26: Distributions to GP | C26: =D8 -> 0 | F26: =F18/$C$18*$C$26 -> 0 | G26: =G18/$C$18*$C$26 -> 0 | H26: =H18/$C$18*$C$26 -> 0 | I26: =I18/$C$18*$C$26 -> 0 | J26: =J18/$C$18*$C$26 -> 0 | K26: =K18/$C$18*$C$26 -> 0 | L26: =L18/$C$18*$C$26 -> 0 | M26: =M18/$C$18*$C$26 -> 0 | ... P26: =P18/$C$18*$C$26 -> 0
B28: Total Distributions Hurdle 1 | F28: =F18+F26 -> 0 | G28: =G18+G26 -> 33413.344 | H28: =H18+H26 -> 89663.456 | I28: =I18+I26 -> 60999.138 | J28: =J18+J26 -> 38876.116 | K28: =K18+K26 -> 36186.225 | L28: =L18+L26 -> 32990.729 | M28: =M18+M26 -> 0 | ... P28: =P18+P26 -> 0
B29: Cash Flow Remaining for Distribution | F29: =MAX(F12,0)-F28 -> 0 | G29: =MAX(G12,0)-G28 -> 0 | H29: =MAX(H12,0)-H28 -> 11234.623 | I29: =MAX(I12,0)-I28 -> 460896.29 | J29: =MAX(J12,0)-J28 -> 56039.398 | K29: =MAX(K12,0)-K28 -> 66572.839 | L29: =MAX(L12,0)-L28 -> 1534433.1 | M29: =MAX(M12,0)-M28 -> 0 | ... P29: =MAX(P12,0)-P28 -> 0
B31: Hurdle 2 (splits 1)
B32: Beginning Balance (LP) | F32: =E37 -> 0 | G32: =F37 -> 1025640 | H32: =G37 -> 992226.66 | I32: =H37 -> 902563.2 | J32: =I37 -> 841564.06 | K32: =J37 -> 802687.95 | L32: =K37 -> 766501.72 | M32: =L37 -> 733510.99 | ... P32: =O37 -> 733510.99
B33: LP Distribution | C33: =C9 -> 0 | F33: =F32*$C33 -> 0 | G33: =G32*$C$33 -> 0 | H33: =H32*$C33 -> 0 | I33: =I32*$C33 -> 0 | J33: =J32*$C33 -> 0 | K33: =K32*$C33 -> 0 | L33: =L32*$C33 -> 0 | M33: =M32*$C33 -> 0 | N33: =N32*$C33 -> 0 | O33: =O32*$C33 -> 0 | P33: =P32*$C33 -> 0
B34: Contributions from LP | C34: =C17 -> 0.9 | F34: =F17 -> 1025640 | G34: =G17 -> 0 | H34: =H17 -> 0 | I34: =I17 -> 0 | J34: =J17 -> 0 | K34: =K17 -> 0 | L34: =L17 -> 0 | M34: =M17 -> 0 | ... P34: =P17 -> 0
B35: Prior Distributions to LP | F35: =F18 -> 0 | G35: =G18 -> 33413.344 | H35: =H18 -> 89663.456 | I35: =I18 -> 60999.138 | J35: =J18 -> 38876.116 | K35: =K18 -> 36186.225 | L35: =L18 -> 32990.729 | M35: =M18 -> 0 | ... P35: =P18 -> 0
B36: Distributions to LP in Hurdle 2 | C36: =E9 -> 0.5 | F36: =IF(OR($C$9=0,$C$9=""),0,MAX(F29,0)*$E$9) -> 0 | G36: =IF(OR($C$9=0,$C$9=""),0,IF(IFERROR(IRR($F$39:F39),0)>=$C$9,0,MAX(G29,0)*$E$9)) -> 0 | H36: =IF(OR($C$9=0,$C$9=""),0,IF(IFERROR(IRR($F$39:G39),0)>=$C$9,0,MAX(H29,0)*$E$9)) -> 0 | I36: =IF(OR($C$9=0,$C$9=""),0,IF(IFERROR(IRR($F$39:H39),0)>=$C$9,0,MAX(I29,0)*$E$9)) -> 0 | J36: =IF(OR($C$9=0,$C$9=""),0,IF(IFERROR(IRR($F$39:I39),0)>=$C$9,0,MAX(J29,0)*$E$9)) -> 0 | K36: =IF(OR($C$9=0,$C$9=""),0,IF(IFERROR(IRR($F$39:J39),0)>=$C$9,0,MAX(K29,0)*$E$9)) -> 0 | L36: =IF(OR($C$9=0,$C$9=""),0,IF(IFERROR(IRR($F$39:K39),0)>=$C$9,0,MAX(L29,0)*$E$9)) -> 0 | M36: =MIN(M32+M33+M34-M35,M29*$C36) -> 0 | N36: =MIN(N32+N33+N34-N35,N29*$C36) -> 0 | O36: =MIN(O32+O33+O34-O35,O29*$C36) -> 0 | P36: =MIN(P32+P33+P34-P35,P29*$C36) -> 0
B37: Ending Balance (LP) | F37: =MAX(0,F32+F34-F35-F36) -> 1025640 | G37: =MAX(0,G32+G34-G35-G36) -> 992226.66 | H37: =MAX(0,H32+H34-H35-H36) -> 902563.2 | I37: =MAX(0,I32+I34-I35-I36) -> 841564.06 | J37: =MAX(0,J32+J34-J35-J36) -> 802687.95 | K37: =MAX(0,K32+K34-K35-K36) -> 766501.72 | L37: =MAX(0,L32+L34-L35-L36) -> 733510.99 | M37: =MAX(0,M32+M34-M35-M36) -> 733510.99 | ... P37: =MAX(0,P32+P34-P35-P36) -> 733510.99
B38: LP Cummulative IRR | C38: =C33 -> 0 | F38: =IFERROR(IRR($F$39:F39),0) -> 0 | G38: =IFERROR(IRR($F$39:G39),0) -> -0.96742196 | H38: =IFERROR(IRR($F$39:H39),0) -> -0.68759058 | I38: =IFERROR(IRR($F$39:I39),0) -> -0.52290144 | J38: =IFERROR(IRR($F$39:J39),0) -> -0.42876626 | K38: =IFERROR(IRR($F$39:K39),0) -> -0.35184948 | L38: =IFERROR(IRR($F$39:L39),0) -> -0.29330078 | M38: =SUM(M35:M36)/SUM($E34:M34) -> 0 | N38: =SUM(N35:N36)/SUM($E34:N34) -> 0 | O38: =SUM(O35:O36)/SUM($E34:O34) -> 0 | P38: =SUM(P35:P36)/SUM($E34:P34) -> 0
B39: LP Net Cash Flows | F39: =-F34+F35+F36 -> -1025640 | G39: =-G34+G35+G36 -> 33413.344 | H39: =-H34+H35+H36 -> 89663.456 | I39: =-I34+I35+I36 -> 60999.138 | J39: =-J34+J35+J36 -> 38876.116 | K39: =-K34+K35+K36 -> 36186.225 | L39: =-L34+L35+L36 -> 32990.729 | M39: =-M34+M35+M36 -> 0 | ... P39: =-P34+P35+P36 -> 0
B40: LP Cumm IRR Check | C40: =IFERROR(IRR(F39:L39),0)>=C38 -> FALSE
B42: Contributions from GP | C42: =C25 -> 0.1 | F42: =F25 -> 113960 | G42: =G25 -> 0 | H42: =H25 -> 0 | I42: =I25 -> 0 | J42: =J25 -> 0 | K42: =K25 -> 0 | L42: =L25 -> 0 | M42: =M25 -> 0 | ... P42: =P25 -> 0
B43: Distributions to GP | C43: =D9 -> 0.5 | F43: =IF(OR($C$9=0,$C$9=""),0,MAX(F29,0)*$D$9) -> 0 | G43: =IF(OR($C$9=0,$C$9=""),0,IF(IFERROR(IRR($F$39:F39),0)>=$C$9,0,MAX(G29,0)*$D$9)) -> 0 | H43: =IF(OR($C$9=0,$C$9=""),0,IF(IFERROR(IRR($F$39:G39),0)>=$C$9,0,MAX(H29,0)*$D$9)) -> 0 | I43: =IF(OR($C$9=0,$C$9=""),0,IF(IFERROR(IRR($F$39:H39),0)>=$C$9,0,MAX(I29,0)*$D$9)) -> 0 | J43: =IF(OR($C$9=0,$C$9=""),0,IF(IFERROR(IRR($F$39:I39),0)>=$C$9,0,MAX(J29,0)*$D$9)) -> 0 | K43: =IF(OR($C$9=0,$C$9=""),0,IF(IFERROR(IRR($F$39:J39),0)>=$C$9,0,MAX(K29,0)*$D$9)) -> 0 | L43: =IF(OR($C$9=0,$C$9=""),0,IF(IFERROR(IRR($F$39:K39),0)>=$C$9,0,MAX(L29,0)*$D$9)) -> 0 | M43: =M36/$C$36*$C$43 -> 0 | N43: =N36/$C$36*$C$43 -> 0 | O43: =O36/$C$36*$C$43 -> 0 | P43: =P36/$C$36*$C$43 -> 0
B45: Total Distributions Hurdle 2 | F45: =F36+F43 -> 0 | G45: =G36+G43 -> 0 | H45: =H36+H43 -> 0 | I45: =I36+I43 -> 0 | J45: =J36+J43 -> 0 | K45: =K36+K43 -> 0 | L45: =L36+L43 -> 0 | M45: =M36+M43 -> 0 | ... P45: =P36+P43 -> 0
B46: Cash Flow Remaining | F46: =MAX(F29,0)-F45 -> 0 | G46: =MAX(G29,0)-G45 -> 0 | H46: =MAX(H29,0)-H45 -> 11234.623 | I46: =MAX(I29,0)-I45 -> 460896.29 | J46: =MAX(J29,0)-J45 -> 56039.398 | K46: =MAX(K29,0)-K45 -> 66572.839 | L46: =MAX(L29,0)-L45 -> 1534433.1 | M46: =MAX(M29,0)-M45 -> 0 | ... P46: =MAX(P29,0)-P45 -> 0
B48: Hurdle 3 (splits 2)
B49: Beginning Balance (LP) | F49: =E54 -> 0 | G49: =F54 -> 1025640 | H49: =G54 -> 992226.66 | I49: =H54 -> 893575.5 | J49: =I54 -> 463859.33 | K49: =J54 -> 380151.7 | L49: =K54 -> 290707.2 | M49: =L54 -> 0 | ... P49: =O54 -> 0
B50: LP Cumulative IRR | C50: =C11 -> 0.15 | F50: =IFERROR(IRR($F$56:F56),0) -> 0 | G50: =IFERROR(IRR($F$56:G56),0) -> -0.96742196 | H50: =IFERROR(IRR($F$56:H56),0) -> -0.67314649 | I50: =IFERROR(IRR($F$56:I56),0) -> -0.19731638 | J50: =IFERROR(IRR($F$56:J56),0) -> -0.14711524 | K50: =IFERROR(IRR($F$56:K56),0) -> -0.09951208 | L50: =IFERROR(IRR($F$56:L56),0) -> 0.14947567 | M50: =M49*$C50 -> 0 | N50: =N49*$C50 -> 0 | O50: =O49*$C50 -> 0 | P50: =P49*$C50 -> 0
B51: Contributions from LP | C51: =C6 -> 0.9 | F51: =F34 -> 1025640 | G51: =G34 -> 0 | H51: =H34 -> 0 | I51: =I34 -> 0 | J51: =J34 -> 0 | K51: =K34 -> 0 | L51: =L34 -> 0 | M51: =M34 -> 0 | ... P51: =P34 -> 0
B52: Prior Distributions to LP | F52: =F35+F36 -> 0 | G52: =G35+G36 -> 33413.344 | H52: =H35+H36 -> 89663.456 | I52: =I35+I36 -> 60999.138 | J52: =J35+J36 -> 38876.116 | K52: =K35+K36 -> 36186.225 | L52: =L35+L36 -> 32990.729 | M52: =M35+M36 -> 0 | ... P52: =P35+P36 -> 0
B53: Distributions to LP in Hurdle 3 | C53: =E10 -> 0.8 | F53: =IF(AND(F49<=0,0>=$C$11), 0, MAX(F46,0)*$E$10) -> 0 | G53: =IF(AND(G49<=0,IFERROR(IRR($F$56:F56),0)>=$C$11),0, MAX(G46,0)*$E$10) -> 0 | H53: =IF(AND(H49<=0,IFERROR(IRR($F$56:G56),0)>=$C$11),0, MAX(H46,0)*$E$10) -> 8987.6983 | I53: =IF(AND(I49<=0,IFERROR(IRR($F$56:H56),0)>=$C$11),0, MAX(I46,0)*$E$10) -> 368717.03 | J53: =IF(AND(J49<=0,IFERROR(IRR($F$56:I56),0)>=$C$11),0, MAX(J46,0)*$E$10) -> 44831.518 | K53: =IF(AND(K49<=0,IFERROR(IRR($F$56:J56),0)>=$C$11),0, MAX(K46,0)*$E$10) -> 53258.271 | L53: =IF(AND(L49<=0,IFERROR(IRR($F$56:K56),0)>=$C$11),0, MAX(L46,0)*$E$10) -> 1227546.5 | M53: =MIN(M49+M50+M51-M52,M46*$C53) -> 0 | N53: =MIN(N49+N50+N51-N52,N46*$C53) -> 0 | O53: =MIN(O49+O50+O51-O52,O46*$C53) -> 0 | P53: =MIN(P49+P50+P51-P52,P46*$C53) -> 0
B54: Ending Balance (LP) | F54: =MAX(0,F49+F51-F52-F53) -> 1025640 | G54: =MAX(0,G49+G51-G52-G53) -> 992226.66 | H54: =MAX(0,H49+H51-H52-H53) -> 893575.5 | I54: =MAX(0,I49+I51-I52-I53) -> 463859.33 | J54: =MAX(0,J49+J51-J52-J53) -> 380151.7 | K54: =MAX(0,K49+K51-K52-K53) -> 290707.2 | L54: =MAX(0,L49+L51-L52-L53) -> 0 | M54: =MAX(0,M49+M50+M51-M53-M52) -> 0 | N54: =MAX(0,N49+N50+N51-N53-N52) -> 0 | O54: =MAX(0,O49+O50+O51-O53-O52) -> 0 | P54: =MAX(0,P49+P50+P51-P53-P52) -> 0
B55: LP Cash/Cash | F55: =IFERROR(SUM(F52:F53)/SUM($E51:F51),0) -> 0 | G55: =IFERROR(SUM(G52:G53)/SUM($E51:G51),0) -> 0.032578043 | H55: =IFERROR(SUM(H52:H53)/SUM($E51:H51),0) -> 0.096184972 | I55: =IFERROR(SUM(I52:I53)/SUM($E51:I51),0) -> 0.41897369 | J55: =IFERROR(SUM(J52:J53)/SUM($E51:J51),0) -> 0.081615025 | K55: =IFERROR(SUM(K52:K53)/SUM($E51:K51),0) -> 0.087208471 | L55: =IFERROR(SUM(L52:L53)/SUM($E51:L51),0) -> 1.229025 | M55: =SUM(M52:M53)/SUM($E51:M51) -> 0 | N55: =SUM(N52:N53)/SUM($E51:N51) -> 0 | O55: =SUM(O52:O53)/SUM($E51:O51) -> 0 | P55: =SUM(P52:P53)/SUM($E51:P51) -> 0
B56: LP Net Cash Flows | F56: =-F51+F52+F53 -> -1025640 | G56: =-G51+G52+G53 -> 33413.344 | H56: =-H51+H52+H53 -> 98651.154 | I56: =-I51+I52+I53 -> 429716.17 | J56: =-J51+J52+J53 -> 83707.635 | K56: =-K51+K52+K53 -> 89444.496 | L56: =-L51+L52+L53 -> 1260537.2 | M56: =-M51+M52+M53 -> 0 | ... P56: =-P51+P52+P53 -> 0
B57: LP IRR Check | C57: =ROUND(IRR(F56:L56),3)=C55 -> FALSE
B59: Contributions from GP | C59: =C5 -> 0.1 | F59: =F42 -> 113960 | G59: =G42 -> 0 | H59: =H42 -> 0 | I59: =I42 -> 0 | J59: =J42 -> 0 | K59: =K42 -> 0 | L59: =L42 -> 0 | M59: =M42 -> 0 | ... P59: =P42 -> 0
B60: Distributions to GP | C60: =D10 -> 0.2 | F60: =IF(AND(F49<=0,IFERROR(IRR(E$56:$F56),0)>=$C$11),MAX(F46,0), MAX(F46,0)*$D$10) -> 0 | G60: =IF(AND(G49<=0,IFERROR(IRR(F$56:$F56),0)>=$C$11),MAX(G46,0), MAX(G46,0)*$D$10) -> 0 | H60: =IF(AND(H49<=0,IFERROR(IRR(G$56:$F56),0)>=$C$11),MAX(H46,0), MAX(H46,0)*$D$10) -> 2246.9246 | I60: =IF(AND(I49<=0,IFERROR(IRR(H$56:$F56),0)>=$C$11),MAX(I46,0), MAX(I46,0)*$D$10) -> 92179.259 | J60: =IF(AND(J49<=0,IFERROR(IRR(I$56:$F56),0)>=$C$11),MAX(J46,0), MAX(J46,0)*$D$10) -> 11207.88 | K60: =IF(AND(K49<=0,IFERROR(IRR(J$56:$F56),0)>=$C$11),MAX(K46,0), MAX(K46,0)*$D$10) -> 13314.568 | L60: =IF(AND(L49<=0,IFERROR(IRR(K$56:$F56),0)>=$C$11),MAX(L46,0), MAX(L46,0)*$D$10) -> 306886.62 | M60: =M53/$C$53*$C$60 -> 0 | N60: =N53/$C$53*$C$60 -> 0 | O60: =O53/$C$53*$C$60 -> 0 | P60: =P53/$C$53*$C$60 -> 0
B62: Total Distributions Hurdle 3 | F62: =F53+F60 -> 0 | G62: =G53+G60 -> 0 | H62: =H53+H60 -> 11234.623 | I62: =I53+I60 -> 460896.29 | J62: =J53+J60 -> 56039.398 | K62: =K53+K60 -> 66572.839 | L62: =L53+L60 -> 1534433.1 | M62: =M53+M60 -> 0 | ... P62: =P53+P60 -> 0
B63: Cash Flow Remaining | F63: =MAX(F46,0)-F62 -> 0 | G63: =MAX(G46,0)-G62 -> 0 | H63: =MAX(H46,0)-H62 -> 0 | I63: =MAX(I46,0)-I62 -> 0 | J63: =MAX(J46,0)-J62 -> 0 | K63: =MAX(K46,0)-K62 -> 0 | L63: =MAX(L46,0)-L62 -> 0 | M63: =MAX(M47,0)-M62 -> 0 | N63: =MAX(N47,0)-N62 -> 0 | O63: =MAX(O47,0)-O62 -> 0 | P63: =MAX(P47,0)-P62 -> 0
B65: GP Cash Flow
B66: Distributions | C66: =SUM(F66:P66) -> 473835.25 | F66: =F26+F43+F60 -> 0 | G66: =G26+G43+G60+INPUTS!R50 -> 48000 | H66: =H26+H43+H60 -> 2246.9246 | I66: =I26+I43+I60 -> 92179.259 | J66: =J26+J43+J60 -> 11207.88 | K66: =K26+K43+K60 -> 13314.568 | L66: =L26+L43+L60 -> 306886.62 | M66: =M26+M43+M60 -> 0 | N66: =N26+N43+N60 -> 0 | O66: =O26+O43+O60 -> 0 | P66: =P26+P43+P60 -> 0
B67: Contributions | C67: =SUM(F67:P67) -> 113960 | D67: IRR | E67: EM | F67: =F25 -> 113960 | G67: =G25 -> 0 | H67: =H25 -> 0 | I67: =I25 -> 0 | J67: =J25 -> 0 | K67: =K25 -> 0 | L67: =L25 -> 0 | M67: =M25 -> 0 | ... P67: =P25 -> 0
B68: Net Cash Flow | C68: =SUM(F68:P68) -> 359875.25 | D68: =IRR(F68:P68) -> 0.40422981 | E68: =C66/C67 -> 4.1579085 | F68: =-F67+F66 -> -113960 | G68: =-G67+G66 -> 48000 | H68: =-H67+H66 -> 2246.9246 | I68: =-I67+I66 -> 92179.259 | J68: =-J67+J66 -> 11207.88 | K68: =-K67+K66 -> 13314.568 | L68: =-L67+L66 -> 306886.62 | M68: =-M67+M66 -> 0 | ... P68: =-P67+P66 -> 0
G69: =G68/$C$67 -> 0.42120042 | H69: =H68/$C$67 -> 0.019716783 | I69: =I68/$C$67 -> 0.8088738 | J69: =J68/$C$67 -> 0.098349242 | K69: =K68/$C$67 -> 0.11683545 | L69: =L68/$C$67 -> 2.6929328 | M69: =M68/$C$67 -> 0 | N69: =N68/$C$67 -> 0 | ... P69: =P68/$C$67 -> 0
B70: LP Cash Flow
B71: Distributions | C71: =SUM(F71:L71) -> 1995470 | F71: =F18+F36+F53 -> 0 | G71: =G18+G36+G53 -> 33413.344 | H71: =H18+H36+H53 -> 98651.154 | I71: =I18+I36+I53 -> 429716.17 | J71: =J18+J36+J53 -> 83707.635 | K71: =K18+K36+K53 -> 89444.496 | L71: =L18+L36+L53 -> 1260537.2 | M71: =M18+M36+M53 -> 0 | ... P71: =P18+P36+P53 -> 0 | Q71: =SUM(C71:M71) -> 3990940
B72: Contributions | C72: =SUM(F72:P72) -> 1025640 | D72: IRR | E72: EM | F72: =F17 -> 1025640 | G72: =G17 -> 0 | H72: =H17 -> 0 | I72: =I17 -> 0 | J72: =J17 -> 0 | K72: =K17 -> 0 | L72: =L17 -> 0 | M72: =M17 -> 0 | ... P72: =P17 -> 0
B73: Net Cash Flow | C73: =SUM(F73:P73) -> 969830.02 | D73: =IRR(F73:P73) -> 0.14947567 | E73: =C71/C72 -> 1.9455852 | F73: =-F72+F71 -> -1025640 | G73: =-G72+G71 -> 33413.344 | H73: =-H72+H71 -> 98651.154 | I73: =-I72+I71 -> 429716.17 | J73: =-J72+J71 -> 83707.635 | K73: =-K72+K71 -> 89444.496 | L73: =-L72+L71 -> 1260537.2 | M73: =-M72+M71 -> 0 | ... P73: =-P72+P71 -> 0
E74: LP Cash-on-cash | F74: 0 | G74: =G73/$C$72 -> 0.032578043 | H74: =H73/$C$72 -> 0.096184972 | I74: =I73/$C$72 -> 0.41897369 | J74: =J73/$C$72 -> 0.081615025 | K74: =K73/$C$72 -> 0.087208471 | L74: =L73/$C$72 -> 1.229025 | M74: =M73/$C$72 -> 0 | N74: =N73/$C$72 -> 0 | ... P74: =P73/$C$72 -> 0
B75: GP 10k Invested Cash Flow | C75: Contribution %
C76: =D76/C67 -> 0.087750088 | D76: 10000
B77: Contribution | C77: =SUM(F77:P77) -> 10000 | F77: =F67*$C76 -> 10000 | G77: =G67*$C76 -> 0 | H77: =H67*$C76 -> 0 | I77: =I67*$C76 -> 0 | J77: =J67*$C76 -> 0 | K77: =K67*$C76 -> 0 | L77: =L67*$C76 -> 0 | M77: =M67*$C76 -> 0 | ... P77: =P67*$C76 -> 0
B78: Distribution | C78: =SUM(F78:P78) -> 41579.085 | D78: IRR | E78: EM | F78: =F$66*$C76 -> 0 | G78: =G$66*$C76 -> 4212.0042 | H78: =H$66*$C76 -> 197.16783 | I78: =I$66*$C76 -> 8088.738 | J78: =J$66*$C76 -> 983.49242 | K78: =K$66*$C76 -> 1168.3545 | L78: =L$66*$C76 -> 26929.328 | M78: =M$66*$C76 -> 0 | ... P78: =P$66*$C76 -> 0
B79: Net Cash Flow | C79: =SUM(F79:P79) -> 31579.085 | D79: =IRR(F79:P79) -> 0.40422981 | E79: =C78/C77 -> 4.1579085 | F79: =F78-F77 -> -10000 | G79: =G78-G77 -> 4212.0042 | H79: =H78-H77 -> 197.16783 | I79: =I78-I77 -> 8088.738 | J79: =J78-J77 -> 983.49242 | K79: =K78-K77 -> 1168.3545 | L79: =L78-L77 -> 26929.328 | M79: =M78-M77 -> 0 | ... P79: =P78-P77 -> 0
B81: LP 10k Invested Cash Flow | C81: Contribution %
C82: =D82/C72 -> 0.0097500098 | D82: 10000
B83: Contribution | C83: =SUM(F83:P83) -> 10000 | F83: =F72*$C82 -> 10000 | G83: =G72*$C82 -> 0 | H83: =H72*$C82 -> 0 | I83: =I72*$C82 -> 0 | J83: =J72*$C82 -> 0 | K83: =K72*$C82 -> 0 | L83: =L72*$C82 -> 0 | M83: =M72*$C82 -> 0 | ... P83: =P72*$C82 -> 0
B84: Distribution | C84: =SUM(F84:P84) -> 19455.852 | D84: IRR | E84: EM | F84: =F71*$C82 -> 0 | G84: =G71*$C82 -> 325.78043 | H84: =H71*$C82 -> 961.84972 | I84: =I71*$C82 -> 4189.7369 | J84: =J71*$C82 -> 816.15025 | K84: =K71*$C82 -> 872.08471 | L84: =L71*$C82 -> 12290.25 | M84: =M71*$C82 -> 0 | ... P84: =P71*$C82 -> 0
B85: Net Cash Flow | C85: =SUM(F85:P85) -> 9455.8522 | D85: =IRR(F85:P85) -> 0.14947567 | E85: =C84/C83 -> 1.9455852 | F85: =F84-F83 -> -10000 | G85: =G84-G83 -> 325.78043 | H85: =H84-H83 -> 961.84972 | I85: =I84-I83 -> 4189.7369 | J85: =J84-J83 -> 816.15025 | K85: =K84-K83 -> 872.08471 | L85: =L84-L83 -> 12290.25 | M85: =M84-M83 -> 0 | ... P85: =P84-P83 -> 0
B88: EXAMPLE RETURNS FOR AN INVESTOR. (INPUT INVESTMENT AMOUNT)
B90: $25,000 Investor Example | C90: Cashflow | F90: -75000 | G90: =$F$91*G73 -> 2443.3532 | H90: =$F$91*H73 -> 7213.8729 | I90: =$F$91*I73 -> 31423.027 | J90: =$F$91*J73 -> 6121.1269 | K90: =$F$91*K73 -> 6540.6353 | L90: =$F$91*L73 -> 92176.876
C91: IRR | D91: =D73 -> 0.14947567 | F91: =F90/F73 -> 0.073125073
C92: Cash/Cash | D92: =AVERAGE(G92:K92) -> 0.14331204 | G92: =G74 -> 0.032578043 | H92: =H74 -> 0.096184972 | I92: =I74 -> 0.41897369 | J92: =J74 -> 0.081615025 | K92: =K74 -> 0.087208471 | L92: =L74 -> 1.229025
C93: ROI/ARR | D93: =((SUM(G90:L90)+F90)/6)/-F90 -> 0.15759754
B95: $100,000 Investor Example | C95: Cashflow | F95: -100000 | G95: =$F$96*G73 -> 3257.8043 | H95: =$F$96*H73 -> 9618.4972 | I95: =$F$96*I73 -> 41897.369 | J95: =$F$96*J73 -> 8161.5025 | K95: =$F$96*K73 -> 8720.8471 | L95: =$F$96*L73 -> 122902.5
C96: IRR | D96: =D73 -> 0.14947567 | F96: =F95/F73 -> 0.097500098
C97: Cash/Cash | D97: =AVERAGE(G97:K97) -> 0.14331204 | G97: =G74 -> 0.032578043 | H97: =H74 -> 0.096184972 | I97: =I74 -> 0.41897369 | J97: =J74 -> 0.081615025 | K97: =K74 -> 0.087208471 | L97: =L74 -> 1.229025
C98: ROI/ARR | D98: =((SUM(G95:L95)+F95)/6)/-F95 -> 0.15759754

Sheet SENIOR LOAN
A1: Amortization Table
B2: A simple amortization table covering 36 payment periods of a loan.
B3: 1) To use the table, simply change any of the values in the "inital data" area of the worksheet.
B4: 2) To print the table, just choose "Print" from the "File" menu. The print area is already defined.
A5: Initial Data
A6: LOAN DATA | E6: TABLE DATA
B7: Loan amount: | C7: =INPUTS!F13 -> 1454400 | F7: Table starts at date:
B8: Annual interest rate: | C8: =INPUTS!F14 -> 0.0675 | F8: or at payment number: | G8: 1
B9: Amortization: | C9: 25 | E9: I/O Period (months):
B10: Payments per year: | C10: 12 | F10: =INPUTS!H12*12 -> 24
B11: First payment due: | C11: 46143
A12: PERIODIC PAYMENT
B13: Interest Only | C13: =E22 -> 8181 | D13: The table uses the calculated periodic payment amount
B14: Full payment: | C14: =-PMT(C8/12,C9*12,C7) -> 10048.617 | D14: unless you enter a value for "Entered payment".
A15: CALCULATIONS
B16: Post-I/O payment: | C16: =IF(INPUTS!H12>0,-PMT(C8/12,C9*12-F10,C7),C14) -> 10390.432
B17: 1st payment in table: | C17: =IF(G7=0,IF(G8=0,1,G8),1+C10*(YEAR(G7)-YEAR(C11))+INT(C10*(MONTH(G7)-MONTH(C11))/12)+IF(DAY(G7)>DAY(C11),1)) -> 1
A18: Table
A20: Year | B20: Month | C20: Payment | D20: Beginning | G20: Ending | H20: Cumulative
A21: No. | B21: No. | C21: Date | D21: Balance | E21: Interest | F21: Principal | G21: Balance | H21: Interest
A22: =ROUNDUP(B22/12,0) -> 1 | B22: 1 | C22: =C11 -> 46143 | D22: =C7 -> 1454400 | E22: =D22*$C$8/12 -> 8181 | F22: =IF(B22<=$F$10,0,$C$16-E22) -> 0 | G22: =D22-F22 -> 1454400 | H22: =SUM($E$22:E22) -> 8181
A23: =ROUNDUP(B23/12,0) -> 1 | B23: =B22+1 -> 2 | C23: =EDATE(C22,1) -> 46174 | D23: =G22 -> 1454400 | E23: =D23*$C$8/12 -> 8181 | F23: =IF(B23<=$F$10,0,$C$16-E23) -> 0 | G23: =D23-F23 -> 1454400 | H23: =SUM($E$22:E23) -> 16362
A24: =ROUNDUP(B24/12,0) -> 1 | B24: =B23+1 -> 3 | C24: =EDATE(C23,1) -> 46204 | D24: =G23 -> 1454400 | E24: =D24*$C$8/12 -> 8181 | F24: =IF(B24<=$F$10,0,$C$16-E24) -> 0 | G24: =D24-F24 -> 1454400 | H24: =SUM($E$22:E24) -> 24543
A25: =ROUNDUP(B25/12,0) -> 1 | B25: =B24+1 -> 4 | C25: =EDATE(C24,1) -> 46235 | D25: =G24 -> 1454400 | E25: =D25*$C$8/12 -> 8181 | F25: =IF(B25<=$F$10,0,$C$16-E25) -> 0 | G25: =D25-F25 -> 1454400 | H25: =SUM($E$22:E25) -> 32724
A26: =ROUNDUP(B26/12,0) -> 1 | B26: =B25+1 -> 5 | C26: =EDATE(C25,1) -> 46266 | D26: =G25 -> 1454400 | E26: =D26*$C$8/12 -> 8181 | F26: =IF(B26<=$F$10,0,$C$16-E26) -> 0 | G26: =D26-F26 -> 1454400 | H26: =SUM($E$22:E26) -> 40905
A27: =ROUNDUP(B27/12,0) -> 1 | B27: =B26+1 -> 6 | C27: =EDATE(C26,1) -> 46296 | D27: =G26 -> 1454400 | E27: =D27*$C$8/12 -> 8181 | F27: =IF(B27<=$F$10,0,$C$16-E27) -> 0 | G27: =D27-F27 -> 1454400 | H27: =SUM($E$22:E27) -> 49086
A28: =ROUNDUP(B28/12,0) -> 1 | B28: =B27+1 -> 7 | C28: =EDATE(C27,1) -> 46327 | D28: =G27 -> 1454400 | E28: =D28*$C$8/12 -> 8181 | F28: =IF(B28<=$F$10,0,$C$16-E28) -> 0 | G28: =D28-F28 -> 1454400 | H28: =SUM($E$22:E28) -> 57267
A29: =ROUNDUP(B29/12,0) -> 1 | B29: =B28+1 -> 8 | C29: =EDATE(C28,1) -> 46357 | D29: =G28 -> 1454400 | E29: =D29*$C$8/12 -> 8181 | F29: =IF(B29<=$F$10,0,$C$16-E29) -> 0 | G29: =D29-F29 -> 1454400 | H29: =SUM($E$22:E29) -> 65448
A30: =ROUNDUP(B30/12,0) -> 1 | B30: =B29+1 -> 9 | C30: =EDATE(C29,1) -> 46388 | D30: =G29 -> 1454400 | E30: =D30*$C$8/12 -> 8181 | F30: =IF(B30<=$F$10,0,$C$16-E30) -> 0 | G30: =D30-F30 -> 1454400 | H30: =SUM($E$22:E30) -> 73629
A31: =ROUNDUP(B31/12,0) -> 1 | B31: =B30+1 -> 10 | C31: =EDATE(C30,1) -> 46419 | D31: =G30 -> 1454400 | E31: =D31*$C$8/12 -> 8181 | F31: =IF(B31<=$F$10,0,$C$16-E31) -> 0 | G31: =D31-F31 -> 1454400 | H31: =SUM($E$22:E31) -> 81810
A32: =ROUNDUP(B32/12,0) -> 1 | B32: =B31+1 -> 11 | C32: =EDATE(C31,1) -> 46447 | D32: =G31 -> 1454400 | E32: =D32*$C$8/12 -> 8181 | F32: =IF(B32<=$F$10,0,$C$16-E32) -> 0 | G32: =D32-F32 -> 1454400 | H32: =SUM($E$22:E32) -> 89991
A33: =ROUNDUP(B33/12,0) -> 1 | B33: =B32+1 -> 12 | C33: =EDATE(C32,1) -> 46478 | D33: =G32 -> 1454400 | E33: =D33*$C$8/12 -> 8181 | F33: =IF(B33<=$F$10,0,$C$16-E33) -> 0 | G33: =D33-F33 -> 1454400 | H33: =SUM($E$22:E33) -> 98172
A34: =ROUNDUP(B34/12,0) -> 2 | B34: =B33+1 -> 13 | C34: =EDATE(C33,1) -> 46508 | D34: =G33 -> 1454400 | E34: =D34*$C$8/12 -> 8181 | F34: =IF(B34<=$F$10,0,$C$16-E34) -> 0 | G34: =D34-F34 -> 1454400 | H34: =SUM($E$22:E34) -> 106353
... A381: =ROUNDUP(B381/12,0) -> 30 | B381: =B380+1 -> 360 | C381: =EDATE(C380,1) -> 57071 | D381: =G380 -> -724621.04 | E381: =D381*$C$8/12 -> -4075.9933 | F381: =IF(B381<=$F$10,0,$C$16-E381) -> 14466.425 | G381: =D381-F381 -> -739087.46 | H381: =SUM($E$22:E381) -> 1494041.7
C382: Total | E382: =SUM(E22:E381) -> 1494041.7 | F382: =SUM(F22:F381) -> 2193487.5

Sheet REFI LOAN
A1: Amortization Table
B2: A simple amortization table covering 36 payment periods of a loan.
B3: 1) To use the table, simply change any of the values in the "inital data" area of the worksheet.
B4: 2) To print the table, just choose "Print" from the "File" menu. The print area is already defined.
A5: Initial Data
A6: LOAN DATA | E6: TABLE DATA
B7: Loan amount: | C7: =INPUTS!R19 -> 1905327.7 | F7: Table starts at date:
B8: Annual interest rate: | C8: =INPUTS!R21 -> 0.0625 | F8: or at payment number: | G8: 1
B9: Term in years: | C9: =INPUTS!R22 -> 25
B10: Payments per year: | C10: 12
B11: First payment due: | C11: =EDATE('SENIOR LOAN'!C11,INPUTS!R15*12) -> 47239
A12: PERIODIC PAYMENT
B13: Interest Only | D13: The table uses the calculated periodic payment amount
B14: Calculated payment: | C14: =-PMT(C8/12,C9*12-INPUTS!R20*12,C7) -> 13030.059 | D14: unless you enter a value for "Entered payment".
A15: CALCULATIONS
B16: Use payment of: | C16: =C14 -> 13030.059
B17: 1st payment in table: | C17: =IF(G7=0,IF(G8=0,1,G8),1+C10*(YEAR(G7)-YEAR(C11))+INT(C10*(MONTH(G7)-MONTH(C11))/12)+IF(DAY(G7)>DAY(C11),1)) -> 1
A18: Table
A20: Year | B20: Month | C20: Payment | D20: Beginning | G20: Ending | H20: Cumulative
A21: No. | B21: No. | C21: Date | D21: Balance | E21: Interest | F21: Principal | G21: Balance | H21: Interest
A22: =ROUNDUP(B22/12,0) -> 4 | B22: =INPUTS!R15*12+1 -> 37 | C22: =C11 -> 47239 | D22: =C7 -> 1905327.7 | E22: =D22*$C$8/12 -> 9923.5816 | F22: =($C$14-E22)*(B22<$C$9*12+$B$22)*(B22>INPUTS!$R$20*12+$B$22-1) -> 0 | G22: =D22-F22 -> 1905327.7 | H22: =SUM($E$22:E22) -> 9923.5816
A23: =ROUNDUP(B23/12,0) -> 4 | B23: =B22+1 -> 38 | C23: =EDATE(C22,1) -> 47270 | D23: =G22 -> 1905327.7 | E23: =D23*$C$8/12 -> 9923.5816 | F23: =($C$14-E23)*(B23<$C$9*12+$B$22)*(B23>INPUTS!$R$20*12+$B$22-1) -> 0 | G23: =D23-F23 -> 1905327.7 | H23: =SUM($E$22:E23) -> 19847.163
A24: =ROUNDUP(B24/12,0) -> 4 | B24: =B23+1 -> 39 | C24: =EDATE(C23,1) -> 47300 | D24: =G23 -> 1905327.7 | E24: =D24*$C$8/12 -> 9923.5816 | F24: =($C$14-E24)*(B24<$C$9*12+$B$22)*(B24>INPUTS!$R$20*12+$B$22-1) -> 0 | G24: =D24-F24 -> 1905327.7 | H24: =SUM($E$22:E24) -> 29770.745
A25: =ROUNDUP(B25/12,0) -> 4 | B25: =B24+1 -> 40 | C25: =EDATE(C24,1) -> 47331 | D25: =G24 -> 1905327.7 | E25: =D25*$C$8/12 -> 9923.5816 | F25: =($C$14-E25)*(B25<$C$9*12+$B$22)*(B25>INPUTS!$R$20*12+$B$22-1) -> 0 | G25: =D25-F25 -> 1905327.7 | H25: =SUM($E$22:E25) -> 39694.326
A26: =ROUNDUP(B26/12,0) -> 4 | B26: =B25+1 -> 41 | C26: =EDATE(C25,1) -> 47362 | D26: =G25 -> 1905327.7 | E26: =D26*$C$8/12 -> 9923.5816 | F26: =($C$14-E26)*(B26<$C$9*12+$B$22)*(B26>INPUTS!$R$20*12+$B$22-1) -> 0 | G26: =D26-F26 -> 1905327.7 | H26: =SUM($E$22:E26) -> 49617.908
A27: =ROUNDUP(B27/12,0) -> 4 | B27: =B26+1 -> 42 | C27: =EDATE(C26,1) -> 47392 | D27: =G26 -> 1905327.7 | E27: =D27*$C$8/12 -> 9923.5816 | F27: =($C$14-E27)*(B27<$C$9*12+$B$22)*(B27>INPUTS!$R$20*12+$B$22-1) -> 0 | G27: =D27-F27 -> 1905327.7 | H27: =SUM($E$22:E27) -> 59541.489
A28: =ROUNDUP(B28/12,0) -> 4 | B28: =B27+1 -> 43 | C28: =EDATE(C27,1) -> 47423 | D28: =G27 -> 1905327.7 | E28: =D28*$C$8/12 -> 9923.5816 | F28: =($C$14-E28)*(B28<$C$9*12+$B$22)*(B28>INPUTS!$R$20*12+$B$22-1) -> 0 | G28: =D28-F28 -> 1905327.7 | H28: =SUM($E$22:E28) -> 69465.071
A29: =ROUNDUP(B29/12,0) -> 4 | B29: =B28+1 -> 44 | C29: =EDATE(C28,1) -> 47453 | D29: =G28 -> 1905327.7 | E29: =D29*$C$8/12 -> 9923.5816 | F29: =($C$14-E29)*(B29<$C$9*12+$B$22)*(B29>INPUTS!$R$20*12+$B$22-1) -> 0 | G29: =D29-F29 -> 1905327.7 | H29: =SUM($E$22:E29) -> 79388.652
A30: =ROUNDUP(B30/12,0) -> 4 | B30: =B29+1 -> 45 | C30: =EDATE(C29,1) -> 47484 | D30: =G29 -> 1905327.7 | E30: =D30*$C$8/12 -> 9923.5816 | F30: =($C$14-E30)*(B30<$C$9*12+$B$22)*(B30>INPUTS!$R$20*12+$B$22-1) -> 0 | G30: =D30-F30 -> 1905327.7 | H30: =SUM($E$22:E30) -> 89312.234
A31: =ROUNDUP(B31/12,0) -> 4 | B31: =B30+1 -> 46 | C31: =EDATE(C30,1) -> 47515 | D31: =G30 -> 1905327.7 | E31: =D31*$C$8/12 -> 9923.5816 | F31: =($C$14-E31)*(B31<$C$9*12+$B$22)*(B31>INPUTS!$R$20*12+$B$22-1) -> 0 | G31: =D31-F31 -> 1905327.7 | H31: =SUM($E$22:E31) -> 99235.816
A32: =ROUNDUP(B32/12,0) -> 4 | B32: =B31+1 -> 47 | C32: =EDATE(C31,1) -> 47543 | D32: =G31 -> 1905327.7 | E32: =D32*$C$8/12 -> 9923.5816 | F32: =($C$14-E32)*(B32<$C$9*12+$B$22)*(B32>INPUTS!$R$20*12+$B$22-1) -> 0 | G32: =D32-F32 -> 1905327.7 | H32: =SUM($E$22:E32) -> 109159.4
A33: =ROUNDUP(B33/12,0) -> 4 | B33: =B32+1 -> 48 | C33: =EDATE(C32,1) -> 47574 | D33: =G32 -> 1905327.7 | E33: =D33*$C$8/12 -> 9923.5816 | F33: =($C$14-E33)*(B33<$C$9*12+$B$22)*(B33>INPUTS!$R$20*12+$B$22-1) -> 0 | G33: =D33-F33 -> 1905327.7 | H33: =SUM($E$22:E33) -> 119082.98
A34: =ROUNDUP(B34/12,0) -> 5 | B34: =B33+1 -> 49 | C34: =EDATE(C33,1) -> 47604 | D34: =G33 -> 1905327.7 | E34: =D34*$C$8/12 -> 9923.5816 | F34: =($C$14-E34)*(B34<$C$9*12+$B$22)*(B34>INPUTS!$R$20*12+$B$22-1) -> 0 | G34: =D34-F34 -> 1905327.7 | H34: =SUM($E$22:E34) -> 129006.56
... A381: =ROUNDUP(B381/12,0) -> 33 | B381: =B380+1 -> 396 | C381: =EDATE(C380,1) -> 58166 | D381: =G380 -> 3.8671715e-09 | E381: =D381*$C$8/12 -> 2.0141518e-11 | F381: =($C$14-E381)*(B381<$C$9*12+$B$22)*(B381>INPUTS!$R$20*12+$B$22-1) -> 0 | G381: =D381-F381 -> 3.8671715e-09 | H381: =SUM($E$22:E381) -> 1929134.6
C382: Total | E382: =SUM(E22:E381) -> 1929134.6 | F382: =SUM(F22:F381) -> 1905327.7

Sheet Lists
A1: Yes
A2: No
